alphareader/__init__.py
alphareader-0.0.7.dist-info/LICENSE
alphareader-0.0.7.dist-info/METADATA
alphareader-0.0.7.dist-info/WHEEL
alphareader-0.0.7.dist-info/top_level.txt
alphareader-0.0.7.dist-info/RECORD
