Metadata-Version: 2.1
Name: alphareader
Version: 0.0.7
Summary: A reader for large files with custom delimiters and encodings
Home-page: https://github.com/canimus/alphareader
Author: Herminio Vazquez
Author-email: canimus@gmail.com
License: UNKNOWN
Platform: UNKNOWN
Classifier: Programming Language :: Python :: 3
Classifier: License :: OSI Approved :: GNU General Public License v3 (GPLv3)
Classifier: Operating System :: OS Independent
Classifier: Topic :: Text Processing
Classifier: Topic :: Utilities
Requires-Python: >=3.6
